openg2p_g2p_bridge_example_bank_celery/__init__.py
openg2p_g2p_bridge_example_bank_celery/app.py
openg2p_g2p_bridge_example_bank_celery/config.py
openg2p_g2p_bridge_example_bank_celery/tasks/__init__.py
openg2p_g2p_bridge_example_bank_celery/tasks/account_statement_generator.py
openg2p_g2p_bridge_example_bank_celery/tasks/batching_request.py
openg2p_g2p_bridge_example_bank_celery/tasks/process_payment.py
openg2p_g2p_bridge_example_bank_celery/utils/__init__.py
openg2p_g2p_bridge_example_bank_celery/utils/mt940_writer.py
openg2p_g2p_bridge_example_bank_celery-1.1.0.dist-info/METADATA
openg2p_g2p_bridge_example_bank_celery-1.1.0.dist-info/WHEEL
openg2p_g2p_bridge_example_bank_celery-1.1.0.dist-info/licenses/LICENSE
openg2p_g2p_bridge_example_bank_celery-1.1.0.dist-info/RECORD
